HISTORY.txt
MANIFEST.in
README.rst
poolbox.ini
requirements.txt
setup.py
poolbox/__init__.py
poolbox/openapi.py
poolbox/pdf_toolbox.py
poolbox/views.py
poolbox.egg-info/PKG-INFO
poolbox.egg-info/SOURCES.txt
poolbox.egg-info/dependency_links.txt
poolbox.egg-info/entry_points.txt
poolbox.egg-info/not-zip-safe
poolbox.egg-info/requires.txt
poolbox.egg-info/top_level.txt
poolbox/templates/stamp.html.j2
poolbox/tests/__init__.py
poolbox/tests/test_pdf_toolbox.py
poolbox/tests/resources/cerfa_13404-06.pdf
poolbox/tests/resources/cerfa_13404-06.pdf.base64
poolbox/tests/resources/cerfa_13410-04.pdf
poolbox/tests/resources/cerfa_13410-04_filled.pdf