Metadata-Version: 1.1
Name: poolbox
Version: 0.1
Summary: PDF Toolbox WebService
Home-page: https://www.atreal.fr
Author: atReal
Author-email: contact@atreal.fr
License: GPLv2
Keywords: web services
Platform: UNKNOWN
Classifier: Programming Language :: Python :: 2.7
Classifier: Framework :: Pylons
Classifier: License :: OSI Approved :: GNU General Public License v2 (GPLv2)
Classifier: Topic :: Internet :: WWW/HTTP
Classifier: Topic :: Internet :: WWW/HTTP :: WSGI :: Application
